{
  "powertab": {
    "cargoLocks": null,
    "date": null,
    "extract": null,
    "name": "powertab",
    "passthru": null,
    "pinned": false,
    "src": {
      "deepClone": false,
      "fetchSubmodules": false,
      "leaveDotGit": false,
      "name": null,
      "owner": "powertab",
      "repo": "powertabeditor",
      "rev": "2.0.21",
      "sha256": "sha256-mYFguVcF7Xb6rXIIMXAUzRYddlvQDRj7zu6on7GGGeA=",
      "sparseCheckout": [],
      "type": "github"
    },
    "version": "2.0.21"
  }
}
