{
  "alacritty.xplr": {
    "branch": "main",
    "description": "Alacritty integration for xplr",
    "homepage": "https://xplr.dev",
    "owner": "sayanarijit",
    "repo": "alacritty.xplr",
    "rev": "96d291c15a5731bbd6550ec0b90d3e529041ca36",
    "sha256": "09jk5a2zia0v436k6i2xwygbrfq62sg9yj1nkhxs5g80x0qb72y7",
    "type": "tarball",
    "url": "https://github.com/sayanarijit/alacritty.xplr/archive/96d291c15a5731bbd6550ec0b90d3e529041ca36.tar.gz",
    "url_template": "https://github.com/<owner>/<repo>/archive/<rev>.tar.gz"
  },
  "command-mode.xplr": {
    "branch": "main",
    "description": "The missing command mode for xplr",
    "homepage": "https://xplr.stck.me/post/28557/Forget-key-bindings-and-get-yourself-a-command-mode",
    "owner": "sayanarijit",
    "repo": "command-mode.xplr",
    "rev": "43d073bb7f3d5b701a3f254084b91a0911df41d2",
    "sha256": "09dpkbs5mckgrzyi7lxxlsmmjy2m51vv8jvphnhl3460cgq35pql",
    "type": "tarball",
    "url": "https://github.com/sayanarijit/command-mode.xplr/archive/43d073bb7f3d5b701a3f254084b91a0911df41d2.tar.gz",
    "url_template": "https://github.com/<owner>/<repo>/archive/<rev>.tar.gz"
  },
  "context-switch.xplr": {
    "branch": "main",
    "description": "Context switch for xplr",
    "homepage": null,
    "owner": "igorepst",
    "repo": "context-switch.xplr",
    "rev": "85ac284b33144540741f48a5a42d3366d00acae9",
    "sha256": "025bwm5b8sfgscyg1ch464adc9ky28yi4scmlk2nx401hdj6y9dg",
    "type": "tarball",
    "url": "https://github.com/igorepst/context-switch.xplr/archive/85ac284b33144540741f48a5a42d3366d00acae9.tar.gz",
    "url_template": "https://github.com/<owner>/<repo>/archive/<rev>.tar.gz"
  },
  "dragon.xplr": {
    "branch": "main",
    "description": "dragon integration for xplr",
    "homepage": "https://xplr.dev",
    "owner": "sayanarijit",
    "repo": "dragon.xplr",
    "rev": "5fbddcb33f7d75a5abd12d27223ac55589863335",
    "sha256": "0c77dr5513r50idhlgyfslwqyhi3vkak8x4r9kicbvqak6xz55hl",
    "type": "tarball",
    "url": "https://github.com/sayanarijit/dragon.xplr/archive/5fbddcb33f7d75a5abd12d27223ac55589863335.tar.gz",
    "url_template": "https://github.com/<owner>/<repo>/archive/<rev>.tar.gz"
  },
  "dua-cli.xplr": {
    "branch": "main",
    "description": "dua-cli integration for xplr",
    "homepage": "https://xplr.dev",
    "owner": "sayanarijit",
    "repo": "dua-cli.xplr",
    "rev": "66ccf983fab7f67d6b00adc0365a2b26550e7f81",
    "sha256": "0zzjbkz94frdav9ni6lypmksan1cki2jz114pbgqvf865xlmff2w",
    "type": "tarball",
    "url": "https://github.com/sayanarijit/dua-cli.xplr/archive/66ccf983fab7f67d6b00adc0365a2b26550e7f81.tar.gz",
    "url_template": "https://github.com/<owner>/<repo>/archive/<rev>.tar.gz"
  },
  "dual-pane.xplr": {
    "branch": "main",
    "description": "Implements support for dual-pane navigation into xplr",
    "homepage": "https://blog.xplr.dev/post/45811/1-2-or-3-panes-choose-a-layout-that-works-for-you",
    "owner": "sayanarijit",
    "repo": "dual-pane.xplr",
    "rev": "2c4106c1cc882ac3f832b77a3c72fdce83e17d72",
    "sha256": "0rj1qhqicqc5sbl8254zn76199wravcsk6m9lh2p5mmk6jj3vgpx",
    "type": "tarball",
    "url": "https://github.com/sayanarijit/dual-pane.xplr/archive/2c4106c1cc882ac3f832b77a3c72fdce83e17d72.tar.gz",
    "url_template": "https://github.com/<owner>/<repo>/archive/<rev>.tar.gz"
  },
  "dysh-style.xplr": {
    "branch": "main",
    "description": "This plugin complements the xplr file manager theme",
    "homepage": null,
    "owner": "dy-sh",
    "repo": "dysh-style.xplr",
    "rev": "12dab25f9410e1c67f09f60c0af030ea5210ea0d",
    "sha256": "16f9jy0pyfrn1zxv643r69amx9mn5q2kj78b2n25m47sp92pvs1m",
    "type": "tarball",
    "url": "https://github.com/dy-sh/dysh-style.xplr/archive/12dab25f9410e1c67f09f60c0af030ea5210ea0d.tar.gz",
    "url_template": "https://github.com/<owner>/<repo>/archive/<rev>.tar.gz"
  },
  "extra-icons.xplr": {
    "branch": "main",
    "description": "Adds (dev)icons to xplr.",
    "homepage": null,
    "owner": "dtomvan",
    "repo": "extra-icons.xplr",
    "rev": "1f27b9a74c23b869fe64d12f3d8c2a1207ff8eb7",
    "sha256": "0archpg0ml0b6rz0jqwaznrv951faizcr752fi3sfjh2mpvwl47p",
    "type": "tarball",
    "url": "https://github.com/dtomvan/extra-icons.xplr/archive/1f27b9a74c23b869fe64d12f3d8c2a1207ff8eb7.tar.gz",
    "url_template": "https://github.com/<owner>/<repo>/archive/<rev>.tar.gz"
  },
  "find.xplr": {
    "branch": "main",
    "description": "An interactive finder plugin to complement map.xplr",
    "homepage": "https://xplr.dev",
    "owner": "sayanarijit",
    "repo": "find.xplr",
    "rev": "5355d213a7063347f219975e71ddca4bdf8085c9",
    "sha256": "0bvcjnfx1nqpzr5jrpl8f4x5wrh20j1jcdlfgszlg063x8523pqw",
    "type": "tarball",
    "url": "https://github.com/sayanarijit/find.xplr/archive/5355d213a7063347f219975e71ddca4bdf8085c9.tar.gz",
    "url_template": "https://github.com/<owner>/<repo>/archive/<rev>.tar.gz"
  },
  "fzf.xplr": {
    "branch": "main",
    "description": "fzf integration for xplr",
    "homepage": "https://xplr.dev",
    "owner": "sayanarijit",
    "repo": "fzf.xplr",
    "rev": "c8991f92946a7c8177d7f82ed939d845746ebaf5",
    "sha256": "1hkqy08j3a6rkkn6dxc9qs474dxbcpqpdikz7c2gdpg9mrmyv6bn",
    "type": "tarball",
    "url": "https://github.com/sayanarijit/fzf.xplr/archive/c8991f92946a7c8177d7f82ed939d845746ebaf5.tar.gz",
    "url_template": "https://github.com/<owner>/<repo>/archive/<rev>.tar.gz"
  },
  "get-rid-of-index.xplr": {
    "branch": "main",
    "description": "This xplr plugin removes the index column",
    "homepage": null,
    "owner": "dy-sh",
    "repo": "get-rid-of-index.xplr",
    "rev": "1a2fce5ad675a616c7c7b7d460de6712e529e81c",
    "sha256": "0vv1in5kimxkq1999pg5g1qy11ni1sy80n5x48axk1x77ahajxcg",
    "type": "tarball",
    "url": "https://github.com/dy-sh/get-rid-of-index.xplr/archive/1a2fce5ad675a616c7c7b7d460de6712e529e81c.tar.gz",
    "url_template": "https://github.com/<owner>/<repo>/archive/<rev>.tar.gz"
  },
  "icons.xplr": {
    "branch": "main",
    "description": "icon theme for xplr file manager",
    "homepage": "",
    "owner": "prncss-xyz",
    "repo": "icons.xplr",
    "rev": "6133ea79c41629591c72fa4c51132f7a3cb30782",
    "sha256": "13df0pl7c2ywn9g3r7xzjpm35sj5dl1iwjx47xmlhrsbnnl8g926",
    "type": "tarball",
    "url": "https://github.com/prncss-xyz/icons.xplr/archive/6133ea79c41629591c72fa4c51132f7a3cb30782.tar.gz",
    "url_template": "https://github.com/<owner>/<repo>/archive/<rev>.tar.gz"
  },
  "map.xplr": {
    "branch": "main",
    "description": "Visually inspect and interactively execute batch commands using xplr",
    "homepage": "https://xplr.stck.me/post/28432/Execute-batch-operations-using-xplr",
    "owner": "sayanarijit",
    "repo": "map.xplr",
    "rev": "ed774d21195246060ae2d9cae83f82c698e9d8e7",
    "sha256": "0a5jm6yfszasvq5sn7f1sap7sdqrs5jclq4rj6zhf0d992bn9v34",
    "type": "tarball",
    "url": "https://github.com/sayanarijit/map.xplr/archive/ed774d21195246060ae2d9cae83f82c698e9d8e7.tar.gz",
    "url_template": "https://github.com/<owner>/<repo>/archive/<rev>.tar.gz"
  },
  "material-landscape.xplr": {
    "branch": "main",
    "description": "xple theme - Material Landscape",
    "homepage": "https://xplr.dev",
    "owner": "sayanarijit",
    "repo": "material-landscape.xplr",
    "rev": "5aed67b4f3d196709d221080067c9feb9a2cf638",
    "sha256": "1bqp9a1ziv1q0m0m00ha8m8nqgxnqjj7pd03mrpbklw65cw4xgr8",
    "type": "tarball",
    "url": "https://github.com/sayanarijit/material-landscape.xplr/archive/5aed67b4f3d196709d221080067c9feb9a2cf638.tar.gz",
    "url_template": "https://github.com/<owner>/<repo>/archive/<rev>.tar.gz"
  },
  "material-landscape2.xplr": {
    "branch": "main",
    "description": "xplr theme - Material Landscape 2",
    "homepage": "https://xplr.dev",
    "owner": "sayanarijit",
    "repo": "material-landscape2.xplr",
    "rev": "4b32ba6e01918033f821862fca15b0a894f20fe5",
    "sha256": "1h6753qz21kqslm1anrqmw0d79h5c7pzpn5j2jcfbgv46xqynbhl",
    "type": "tarball",
    "url": "https://github.com/sayanarijit/material-landscape2.xplr/archive/4b32ba6e01918033f821862fca15b0a894f20fe5.tar.gz",
    "url_template": "https://github.com/<owner>/<repo>/archive/<rev>.tar.gz"
  },
  "nuke.xplr": {
    "branch": "main",
    "description": "xplr file viewer and opener",
    "homepage": "",
    "owner": "Junker",
    "repo": "nuke.xplr",
    "rev": "f83a7ed58a7212771b15fbf1fdfb0a07b23c81e9",
    "sha256": "0zgyy3knpw3irrfyyc641pgnv2p99gx0rdb56c0zcd4qsixspz4k",
    "type": "tarball",
    "url": "https://github.com/Junker/nuke.xplr/archive/f83a7ed58a7212771b15fbf1fdfb0a07b23c81e9.tar.gz",
    "url_template": "https://github.com/<owner>/<repo>/archive/<rev>.tar.gz"
  },
  "nvim-ctrl.xplr": {
    "branch": "main",
    "description": "Send files to running Neovim sessions using nvim-ctrl",
    "homepage": "https://xplr.dev",
    "owner": "sayanarijit",
    "repo": "nvim-ctrl.xplr",
    "rev": "bbf5e732f228a3086ae7f877d1f27f1c954a8d2f",
    "sha256": "0yammi3a1n1l96rxzwy75m5l1xdpdai7216biz03l5y4lifw9svw",
    "type": "tarball",
    "url": "https://github.com/sayanarijit/nvim-ctrl.xplr/archive/bbf5e732f228a3086ae7f877d1f27f1c954a8d2f.tar.gz",
    "url_template": "https://github.com/<owner>/<repo>/archive/<rev>.tar.gz"
  },
  "offline-docs.xplr": {
    "branch": "main",
    "description": "Fetch the appropriate version of xplr docs and browse offline",
    "homepage": "https://xplr.dev",
    "owner": "sayanarijit",
    "repo": "offline-docs.xplr",
    "rev": "cba060b5a009696fe1b2ccbdd73d7ba2e2d7b51d",
    "sha256": "0yciag726rsnn1hp2k3j130xzbmczid3cps86ky96gp78sf6wags",
    "type": "tarball",
    "url": "https://github.com/sayanarijit/offline-docs.xplr/archive/cba060b5a009696fe1b2ccbdd73d7ba2e2d7b51d.tar.gz",
    "url_template": "https://github.com/<owner>/<repo>/archive/<rev>.tar.gz"
  },
  "one-table-column.xplr": {
    "branch": "main",
    "description": null,
    "homepage": null,
    "owner": "duganchen",
    "repo": "one-table-column.xplr",
    "rev": "795e43efe54e25dc4dd4809ab26cdfd00737dbf9",
    "sha256": "0lph9rx84mnlsmhwz9m9yd21banb7j1yglsw1xbdjy0m5cd80kqi",
    "type": "tarball",
    "url": "https://github.com/duganchen/one-table-column.xplr/archive/795e43efe54e25dc4dd4809ab26cdfd00737dbf9.tar.gz",
    "url_template": "https://github.com/<owner>/<repo>/archive/<rev>.tar.gz"
  },
  "ouch.xplr": {
    "branch": "main",
    "description": "xplr wrapper for https://github.com/ouch-org/ouch",
    "homepage": null,
    "owner": "dtomvan",
    "repo": "ouch.xplr",
    "rev": "375edf19ff3e0286bd7a101b9e4dd24fa5abaeb8",
    "sha256": "1fvwhn6ycqsscbb5cs8jq7f85df3jdfpm3bda7z548hq68mm0qb0",
    "type": "tarball",
    "url": "https://github.com/dtomvan/ouch.xplr/archive/375edf19ff3e0286bd7a101b9e4dd24fa5abaeb8.tar.gz",
    "url_template": "https://github.com/<owner>/<repo>/archive/<rev>.tar.gz"
  },
  "paste-rs.xplr": {
    "branch": "main",
    "description": null,
    "homepage": null,
    "owner": "dtomvan",
    "repo": "paste-rs.xplr",
    "rev": "5101f57dae47d7c7002d69c61dc4774ac76c06be",
    "sha256": "02a8dr2aq91ywcfkciscnydayhy85yv7jjcgvq63v4dip7cpyxyz",
    "type": "tarball",
    "url": "https://github.com/dtomvan/paste-rs.xplr/archive/5101f57dae47d7c7002d69c61dc4774ac76c06be.tar.gz",
    "url_template": "https://github.com/<owner>/<repo>/archive/<rev>.tar.gz"
  },
  "preview-tabbed.xplr": {
    "branch": "main",
    "description": "Previewer implementation for xplr using suckless tabbed and nnn preview-tabbed",
    "homepage": "https://xplr.dev",
    "owner": "sayanarijit",
    "repo": "preview-tabbed.xplr",
    "rev": "1d350e792a21828b3b58e0a0106c36abbe2d6ba3",
    "sha256": "0h82siwwx4d8jf542ilihbjbbpnhb9xrshkmbybv47fx3kv0qs9s",
    "type": "tarball",
    "url": "https://github.com/sayanarijit/preview-tabbed.xplr/archive/1d350e792a21828b3b58e0a0106c36abbe2d6ba3.tar.gz",
    "url_template": "https://github.com/<owner>/<repo>/archive/<rev>.tar.gz"
  },
  "qrcp.xplr": {
    "branch": "main",
    "description": "qrcp integration for xplr",
    "homepage": "https://xplr.dev",
    "owner": "sayanarijit",
    "repo": "qrcp.xplr",
    "rev": "d8cf4f9b57ae10b59c213eb46c5ff5aed793b3ac",
    "sha256": "0rxidswqlqaxa9wb62ym7ds9p3mca782gfd9cmkryhyzsb4w6465",
    "type": "tarball",
    "url": "https://github.com/sayanarijit/qrcp.xplr/archive/d8cf4f9b57ae10b59c213eb46c5ff5aed793b3ac.tar.gz",
    "url_template": "https://github.com/<owner>/<repo>/archive/<rev>.tar.gz"
  },
  "regex-search.xplr": {
    "branch": "main",
    "description": "Bring back the regex based seach in xplr",
    "homepage": "https://xplr.dev",
    "owner": "sayanarijit",
    "repo": "regex-search.xplr",
    "rev": "a0273d384deb8c774104dd0f636927cd35b45f30",
    "sha256": "13m4hmnnbcx5kbhr8yjczqz9wsiwpnn19al6k0kfdqzdlsmvs18z",
    "type": "tarball",
    "url": "https://github.com/sayanarijit/regex-search.xplr/archive/a0273d384deb8c774104dd0f636927cd35b45f30.tar.gz",
    "url_template": "https://github.com/<owner>/<repo>/archive/<rev>.tar.gz"
  },
  "registers.xplr": {
    "branch": "main",
    "description": "Use multiple registers to store the selected paths",
    "homepage": "https://xplr.dev",
    "owner": "sayanarijit",
    "repo": "registers.xplr",
    "rev": "5dd91429fe482163a718dc98cd8fb6570fc1c205",
    "sha256": "0a0v9c5ywk9gy75grsndm8kaxnh62v15r8qv8zy151hdqq89wa35",
    "type": "tarball",
    "url": "https://github.com/sayanarijit/registers.xplr/archive/5dd91429fe482163a718dc98cd8fb6570fc1c205.tar.gz",
    "url_template": "https://github.com/<owner>/<repo>/archive/<rev>.tar.gz"
  },
  "scp.xplr": {
    "branch": "main",
    "description": "Integrate xplr with scp",
    "homepage": "https://xplr.dev",
    "owner": "sayanarijit",
    "repo": "scp.xplr",
    "rev": "578bfd6bd379b113ce63bb0f73658eef2594c817",
    "sha256": "0xl9jq6kgvfh9kdpghc75i6cpc6wn3vic17pljba6w7v0ljvbxhk",
    "type": "tarball",
    "url": "https://github.com/sayanarijit/scp.xplr/archive/578bfd6bd379b113ce63bb0f73658eef2594c817.tar.gz",
    "url_template": "https://github.com/<owner>/<repo>/archive/<rev>.tar.gz"
  },
  "style.xplr": {
    "branch": "main",
    "description": null,
    "homepage": null,
    "owner": "emsquid",
    "repo": "style.xplr",
    "rev": "e1fbd803e8a1dc4a6a1460816b485fb06412e6b8",
    "sha256": "0q1f2bg6apxdd8076qzdbw46ff586pbcb0da4lab1dga1p23xzbq",
    "type": "tarball",
    "url": "https://github.com/emsquid/style.xplr/archive/e1fbd803e8a1dc4a6a1460816b485fb06412e6b8.tar.gz",
    "url_template": "https://github.com/<owner>/<repo>/archive/<rev>.tar.gz"
  },
  "term.xplr": {
    "branch": "main",
    "description": "Terminal integration for xplr",
    "homepage": "https://xplr.dev",
    "owner": "dtomvan",
    "repo": "term.xplr",
    "rev": "870736bb2ca4635de06b8986e761baaf705eb2a7",
    "sha256": "1gwraizlz11ddp4s1bsg2xwnf1pys4wlai63nhnxx2hvl8gb4x3f",
    "type": "tarball",
    "url": "https://github.com/dtomvan/term.xplr/archive/870736bb2ca4635de06b8986e761baaf705eb2a7.tar.gz",
    "url_template": "https://github.com/<owner>/<repo>/archive/<rev>.tar.gz"
  },
  "trash-cli.xplr": {
    "branch": "main",
    "description": "trach-cli integration for xplr",
    "homepage": "https://xplr.dev",
    "owner": "sayanarijit",
    "repo": "trash-cli.xplr",
    "rev": "2c5c8c64ec88c038e2075db3b1c123655dc446fa",
    "sha256": "1d833335p1avsrh5x91wkygy3wcyydzkr84vxh5m0kakbrwadgk1",
    "type": "tarball",
    "url": "https://github.com/sayanarijit/trash-cli.xplr/archive/2c5c8c64ec88c038e2075db3b1c123655dc446fa.tar.gz",
    "url_template": "https://github.com/<owner>/<repo>/archive/<rev>.tar.gz"
  },
  "tree-view.xplr": {
    "branch": "main",
    "description": "Hackable tree view for xplr",
    "homepage": "https://blog.xplr.dev/post/103969/When-you-need-a-tree-view",
    "owner": "sayanarijit",
    "repo": "tree-view.xplr",
    "rev": "eeba82a862ca296db253d7319caf730ce1f034c2",
    "sha256": "11chpxvqw967wq579bj8l62l8gs37ybylmxf75z735xrk2x87lmz",
    "type": "tarball",
    "url": "https://github.com/sayanarijit/tree-view.xplr/archive/eeba82a862ca296db253d7319caf730ce1f034c2.tar.gz",
    "url_template": "https://github.com/<owner>/<repo>/archive/<rev>.tar.gz"
  },
  "tri-pane.xplr": {
    "branch": "main",
    "description": "xplr plugin that implements ranger-like three pane layout",
    "homepage": "https://blog.xplr.dev/post/45811/1-2-or-3-panes-choose-a-layout-that-works-for-you",
    "owner": "sayanarijit",
    "repo": "tri-pane.xplr",
    "rev": "d90c65eb2bdd182f09db2db8969a99666f90c78b",
    "sha256": "15zp7m3x6li46m79a6y6q4a4978snm3lhgh40zljlrhq6mcp7smd",
    "type": "tarball",
    "url": "https://github.com/sayanarijit/tri-pane.xplr/archive/d90c65eb2bdd182f09db2db8969a99666f90c78b.tar.gz",
    "url_template": "https://github.com/<owner>/<repo>/archive/<rev>.tar.gz"
  },
  "type-to-nav.xplr": {
    "branch": "main",
    "description": "type-to-nav port for xplr",
    "homepage": null,
    "owner": "sayanarijit",
    "repo": "type-to-nav.xplr",
    "rev": "de817bd19c56b7cbb1c39c05e4412b7f188b548c",
    "sha256": "1bn6fl95269v8rs2ibzqab7fmgsj0ridn9sc2zvya98b91ghc4h4",
    "type": "tarball",
    "url": "https://github.com/sayanarijit/type-to-nav.xplr/archive/de817bd19c56b7cbb1c39c05e4412b7f188b548c.tar.gz",
    "url_template": "https://github.com/<owner>/<repo>/archive/<rev>.tar.gz"
  },
  "wl-clipboard.xplr": {
    "branch": "main",
    "description": "Copy and paste with system clipboard using wl-clipboard",
    "homepage": "https://xplr.dev",
    "owner": "sayanarijit",
    "repo": "wl-clipboard.xplr",
    "rev": "a3ffc87460c5c7f560bffea689487ae14b36d9c3",
    "sha256": "0jvj1f6ssqnv80lk39z9ivj1cz3lj4xkqqihlfbiixick7jy32i3",
    "type": "tarball",
    "url": "https://github.com/sayanarijit/wl-clipboard.xplr/archive/a3ffc87460c5c7f560bffea689487ae14b36d9c3.tar.gz",
    "url_template": "https://github.com/<owner>/<repo>/archive/<rev>.tar.gz"
  },
  "xclip.xplr": {
    "branch": "main",
    "description": "xclip based copy-paste integration for xplr",
    "homepage": "https://xplr.dev",
    "owner": "sayanarijit",
    "repo": "xclip.xplr",
    "rev": "ddbcce2a255537ce8e3680575bbe964b49d05979",
    "sha256": "1di6zqvc8f94a7khck2y9c59ajpx4vsyyfcb3a9zmggsc7ki6rpm",
    "type": "tarball",
    "url": "https://github.com/sayanarijit/xclip.xplr/archive/ddbcce2a255537ce8e3680575bbe964b49d05979.tar.gz",
    "url_template": "https://github.com/<owner>/<repo>/archive/<rev>.tar.gz"
  },
  "xpm.xplr": {
    "branch": "main",
    "description": "The XPLR Plugin Manager",
    "homepage": null,
    "owner": "dtomvan",
    "repo": "xpm.xplr",
    "rev": "a567f3f73ef0b9bad2c60f6b2b379d70fcf5c5c0",
    "sha256": "16zbf9xkxjxax5x59i3ichrfm9w75d24k7mpc3k8pvcz6c3m339g",
    "type": "tarball",
    "url": "https://github.com/dtomvan/xpm.xplr/archive/a567f3f73ef0b9bad2c60f6b2b379d70fcf5c5c0.tar.gz",
    "url_template": "https://github.com/<owner>/<repo>/archive/<rev>.tar.gz"
  },
  "zentable.xplr": {
    "branch": "main",
    "description": "A clean, distraction free xplr table UI",
    "homepage": "https://blog.xplr.dev/post/45811/1-2-or-3-panes-choose-a-layout-that-works-for-you",
    "owner": "sayanarijit",
    "repo": "zentable.xplr",
    "rev": "6e247bc75fc97a0b80290ae4ce4301241e298c4f",
    "sha256": "02l5mcn77da01vpj6x2ycr95f9iv18vww1k2434ky1iphw2rm2ca",
    "type": "tarball",
    "url": "https://github.com/sayanarijit/zentable.xplr/archive/6e247bc75fc97a0b80290ae4ce4301241e298c4f.tar.gz",
    "url_template": "https://github.com/<owner>/<repo>/archive/<rev>.tar.gz"
  },
  "zoxide.xplr": {
    "branch": "main",
    "description": "zoxide integration for xplr",
    "homepage": "https://xplr.dev",
    "owner": "sayanarijit",
    "repo": "zoxide.xplr",
    "rev": "e50fd35db5c05e750a74c8f54761922464c1ad5f",
    "sha256": "0xj6awk8iqx86svq7hpbslaw02wlsksixjcdbhrzgasmgykaw8v6",
    "type": "tarball",
    "url": "https://github.com/sayanarijit/zoxide.xplr/archive/e50fd35db5c05e750a74c8f54761922464c1ad5f.tar.gz",
    "url_template": "https://github.com/<owner>/<repo>/archive/<rev>.tar.gz"
  }
}
