{
  "name": "proton-cachyos",
  "source": {
    "type": "github-release",
    "repo": "CachyOS/proton-cachyos",
    "skipPrerelease": true
  },
  "asset": {
    "file": "proton-{version}-x86_64{0}.tar.xz",
    "unpack": true
  },
  "force": true,
  "version": "cachyos-10.0-20260203-slr",
  "variants": {
    "v1": {
      "substitutions": [
        ""
      ],
      "hash": "sha256-+YlErTAZFUWLpz5xFwrfG9Ntj644KjORTJlJ8wD5TeU="
    },
    "v2": {
      "substitutions": [
        "_v2"
      ],
      "hash": "sha256-+1EaPudy2L2KPo4xsmk2WYiegAASZAww8LjY84Crhuk="
    },
    "v3": {
      "substitutions": [
        "_v3"
      ],
      "hash": "sha256-dUUQ3V1XfkRbLFKLA5VOF3CsqrnC3Nw17VBryHVHDNY="
    },
    "v4": {
      "substitutions": [
        "_v4"
      ],
      "hash": "sha256-vmPr6hXPvl5pIVmVkdbUWKZm/ZEefT2/2PDUzQAFLU0="
    }
  }
}