{
    "HVM": {
        "branch": "master",
        "description": "A massively parallel, optimal functional runtime in Rust",
        "homepage": "",
        "owner": "kindelia",
        "repo": "HVM",
        "rev": "4345d5baf9b49b3ca59dfbcef00199baebcb038a",
        "sha256": "1kbj07lj89xf446carp7z74999y6gbds8fm7zx13qwa8jfs6wang",
        "type": "tarball",
        "url": "https://github.com/kindelia/HVM/archive/4345d5baf9b49b3ca59dfbcef00199baebcb038a.tar.gz",
        "url_template": "https://github.com/<owner>/<repo>/archive/<rev>.tar.gz"
    },
    "NUR": {
        "branch": "master",
        "description": "Nix User Repository: User contributed nix packages [maintainer=@Mic92]",
        "homepage": "",
        "owner": "nix-community",
        "repo": "NUR",
        "rev": "c3836a37186a240e5792891811ff2219d8c3f7ae",
        "sha256": "1mfkkgvaiif6h75l8x9vwrhq0qrh35gyjmk55y4p4h906arfcn5a",
        "type": "tarball",
        "url": "https://github.com/nix-community/NUR/archive/c3836a37186a240e5792891811ff2219d8c3f7ae.tar.gz",
        "url_template": "https://github.com/<owner>/<repo>/archive/<rev>.tar.gz"
    },
    "classicube": {
        "branch": "master",
        "description": "Custom Minecraft Classic / ClassiCube client written in C (formerly ClassicalSharp in C#) from scratch.",
        "homepage": "",
        "owner": "unknownshadow200",
        "repo": "classicube",
        "rev": "922110ec43efbca217b943cd6f5d9d5292671c01",
        "sha256": "0q66nkb45pdlgw7c1d9vql07wr4p9f9nmkk6y1p2910bsysjw3pa",
        "type": "tarball",
        "url": "https://github.com/unknownshadow200/classicube/archive/922110ec43efbca217b943cd6f5d9d5292671c01.tar.gz",
        "url_template": "https://github.com/<owner>/<repo>/archive/<rev>.tar.gz"
    },
    "dream2nix": {
        "branch": "main",
        "description": "A generic framework for 2nix tools [maintainer=@DavHau]",
        "flake": true,
        "homepage": "",
        "owner": "nix-community",
        "repo": "dream2nix",
        "rev": "0131c22c369f8c4c661aea7a395e94669a7f5974",
        "sha256": "1yinnv1ncjy6203fa58v7whgvwprkg8rdafrs8p3zbjvbc5vrjmv",
        "type": "tarball",
        "url": "https://github.com/nix-community/dream2nix/archive/0131c22c369f8c4c661aea7a395e94669a7f5974.tar.gz",
        "url_template": "https://github.com/<owner>/<repo>/archive/<rev>.tar.gz"
    },
    "efm-langserver": {
        "branch": "master",
        "description": "General purpose Language Server",
        "homepage": "",
        "owner": "mattn",
        "repo": "efm-langserver",
        "rev": "78b0d94d80059462cdecc3012e9812925487ad3d",
        "sha256": "046f6219a5wfgx3mgn1givl0drrna4c7p16xpsqsh598q3q788zv",
        "type": "tarball",
        "url": "https://github.com/mattn/efm-langserver/archive/78b0d94d80059462cdecc3012e9812925487ad3d.tar.gz",
        "url_template": "https://github.com/<owner>/<repo>/archive/<rev>.tar.gz"
    },
    "emacs": {
        "branch": "master",
        "description": null,
        "homepage": null,
        "owner": "crazazy",
        "repo": "emacs",
        "rev": "77b2c7bc57878a55bf0fba69207fb84819606f10",
        "sha256": "0z5v22wbxn4c9aarrq8lb9bwz9z30kgsszq3lk7p1gg10j5h9vdj",
        "type": "tarball",
        "url": "https://github.com/crazazy/emacs/archive/77b2c7bc57878a55bf0fba69207fb84819606f10.tar.gz",
        "url_template": "https://github.com/<owner>/<repo>/archive/<rev>.tar.gz"
    },
    "flake-utils": {
        "branch": "master",
        "description": "Pure Nix flake utility functions",
        "flake": true,
        "homepage": null,
        "owner": "numtide",
        "repo": "flake-utils",
        "rev": "c0e246b9b83f637f4681389ecabcb2681b4f3af0",
        "sha256": "0rq21mnxq8wkwsgjbrqpq4ph062qfprd7m0zy3hysq5pmbqmnnff",
        "type": "tarball",
        "url": "https://github.com/numtide/flake-utils/archive/c0e246b9b83f637f4681389ecabcb2681b4f3af0.tar.gz",
        "url_template": "https://github.com/<owner>/<repo>/archive/<rev>.tar.gz"
    },
    "gitignore": {
        "branch": "master",
        "description": "Nix function for filtering local git sources",
        "homepage": "",
        "owner": "hercules-ci",
        "repo": "gitignore",
        "rev": "a20de23b925fd8264fd7fad6454652e142fd7f73",
        "sha256": "07vg2i9va38zbld9abs9lzqblz193vc5wvqd6h7amkmwf66ljcgh",
        "type": "tarball",
        "url": "https://github.com/hercules-ci/gitignore/archive/a20de23b925fd8264fd7fad6454652e142fd7f73.tar.gz",
        "url_template": "https://github.com/<owner>/<repo>/archive/<rev>.tar.gz"
    },
    "grin": {
        "branch": "master",
        "description": "GRIN is a compiler back-end for lazy and strict functional languages with whole program optimization support.",
        "homepage": "https://grin-compiler.github.io/",
        "owner": "grin-compiler",
        "repo": "grin",
        "rev": "2752657ae8b4053db2ed00f490b49346e5c0c047",
        "sha256": "1r5xnlfl2iq8w9j8w4rsh26s8dbq5ci7zza7zs7wz36a61x6mqpw",
        "type": "tarball",
        "url": "https://github.com/grin-compiler/grin/archive/2752657ae8b4053db2ed00f490b49346e5c0c047.tar.gz",
        "url_template": "https://github.com/<owner>/<repo>/archive/<rev>.tar.gz"
    },
    "home-manager": {
        "branch": "master",
        "description": "Manage a user environment using Nix",
        "flake": true,
        "homepage": "https://rycee.gitlab.io/home-manager/",
        "owner": "rycee",
        "repo": "home-manager",
        "rev": "0884d6c6e47e75bdd1c40045d4d73e7f6c8e5cb8",
        "sha256": "0z1dkjn062d1jbsqzmc7lirb86wjrs47fwzadrl57zqyc4fzijm7",
        "type": "tarball",
        "url": "https://github.com/rycee/home-manager/archive/0884d6c6e47e75bdd1c40045d4d73e7f6c8e5cb8.tar.gz",
        "url_template": "https://github.com/<owner>/<repo>/archive/<rev>.tar.gz"
    },
    "impermanence": {
        "branch": "master",
        "description": "Modules to help you handle persistent state on systems with ephemeral root storage [maintainer=@talyz]",
        "flake": true,
        "homepage": "",
        "owner": "nix-community",
        "repo": "impermanence",
        "rev": "e7c6fbbe9076109263175ef992ca6edc1050973c",
        "sha256": "1axwj83pn0mm1cqwx5ngrg1lz9pna2ygq348vwqc457fl317iwp8",
        "type": "tarball",
        "url": "https://github.com/nix-community/impermanence/archive/e7c6fbbe9076109263175ef992ca6edc1050973c.tar.gz",
        "url_template": "https://github.com/<owner>/<repo>/archive/<rev>.tar.gz"
    },
    "napalm": {
        "branch": "master",
        "description": "Support for building npm packages in Nix and lightweight npm registry",
        "flake": true,
        "homepage": "",
        "owner": "nix-community",
        "repo": "napalm",
        "rev": "4717e59f702303704b46b1e27ede6f17aa4f0f6c",
        "sha256": "14y0l2in8hjxf35f0fgmirl512q7bj2fzy8vn6rh9gxflz93b737",
        "type": "tarball",
        "url": "https://github.com/nix-community/napalm/archive/4717e59f702303704b46b1e27ede6f17aa4f0f6c.tar.gz",
        "url_template": "https://github.com/<owner>/<repo>/archive/<rev>.tar.gz"
    },
    "niv": {
        "branch": "master",
        "description": "Easy dependency management for Nix projects",
        "homepage": "https://github.com/nmattia/niv",
        "owner": "nmattia",
        "repo": "niv",
        "rev": "82e5cd1ad3c387863f0545d7591512e76ab0fc41",
        "sha256": "090l219mzc0gi33i3psgph6s2pwsc8qy4lyrqjdj4qzkvmaj65a7",
        "type": "tarball",
        "url": "https://github.com/nmattia/niv/archive/82e5cd1ad3c387863f0545d7591512e76ab0fc41.tar.gz",
        "url_template": "https://github.com/<owner>/<repo>/archive/<rev>.tar.gz"
    },
    "nix-doom-emacs": {
        "branch": "master",
        "description": "doom-emacs packaged for Nix",
        "flake": true,
        "homepage": "",
        "owner": "vlaci",
        "repo": "nix-doom-emacs",
        "rev": "fee14d217b7a911aad507679dafbeaa8c1ebf5ff",
        "sha256": "1g0izscjh5nv4n0n1m58jc6z27i9pkbxs17mnb05a83ffdbmmva6",
        "type": "tarball",
        "url": "https://github.com/vlaci/nix-doom-emacs/archive/fee14d217b7a911aad507679dafbeaa8c1ebf5ff.tar.gz",
        "url_template": "https://github.com/<owner>/<repo>/archive/<rev>.tar.gz"
    },
    "nix-gen-node-tools": {
        "branch": "master",
        "description": "generate nix expressions for downloading node CLI tools",
        "homepage": null,
        "owner": "crazazy",
        "repo": "nix-gen-node-tools",
        "rev": "00a82576a233c476e6e16be00b782689cd549a5b",
        "sha256": "17bj5qqw9r0yjcw3l9c9z0bik0h6hbzvy23hlsn9xpfcy9zm0v87",
        "type": "tarball",
        "url": "https://github.com/crazazy/nix-gen-node-tools/archive/00a82576a233c476e6e16be00b782689cd549a5b.tar.gz",
        "url_template": "https://github.com/<owner>/<repo>/archive/<rev>.tar.gz"
    },
    "nixpkgs": {
        "branch": "nixos-unstable",
        "description": "Nix Packages collection",
        "flake": true,
        "homepage": "",
        "owner": "nixos",
        "repo": "nixpkgs",
        "rev": "b784c5ae63dd288375af1b4d37b8a27dd8061887",
        "sha256": "0ikm5ch8vnpkc63cw56nkhkrxikxy3dj42029wjshwy375jgldq6",
        "type": "tarball",
        "url": "https://github.com/nixos/nixpkgs/archive/b784c5ae63dd288375af1b4d37b8a27dd8061887.tar.gz",
        "url_template": "https://github.com/<owner>/<repo>/archive/<rev>.tar.gz"
    },
    "nixvim": {
        "branch": "main",
        "description": "Configure Neovim with Nix!",
        "flake": true,
        "homepage": "https://pta2002.github.io/nixvim",
        "owner": "pta2002",
        "repo": "nixvim",
        "rev": "3bb3b7efb5359f79a223a31ada774c937b7f4a96",
        "sha256": "0wfsankr6d94mdxdxv5pzf9s1mmwxf363fhm39xg8lr75pqw264m",
        "type": "tarball",
        "url": "https://github.com/pta2002/nixvim/archive/3bb3b7efb5359f79a223a31ada774c937b7f4a96.tar.gz",
        "url_template": "https://github.com/<owner>/<repo>/archive/<rev>.tar.gz"
    }
}
