{
    "NUR": {
        "branch": "master",
        "description": "Nix User Repository: User contributed nix packages [maintainer=@Mic92]",
        "homepage": "",
        "owner": "nix-community",
        "repo": "NUR",
        "rev": "b0f6ed88d9c04fa521a283febdb9e21bd6da8a4b",
        "sha256": "0qpdgbc5lcnvh7223sjyhnff9mghhd95hjwq04v0px5cp96ncccz",
        "type": "tarball",
        "url": "https://github.com/nix-community/NUR/archive/b0f6ed88d9c04fa521a283febdb9e21bd6da8a4b.tar.gz",
        "url_template": "https://github.com/<owner>/<repo>/archive/<rev>.tar.gz"
    },
    "classicube": {
        "branch": "master",
        "description": "Custom Minecraft Classic / ClassiCube client written in C (formerly ClassicalSharp in C#) from scratch.",
        "homepage": "",
        "owner": "unknownshadow200",
        "repo": "classicube",
        "rev": "a7647a1ba1a7eaadf53973eddc821bdfab6a1206",
        "sha256": "0jkss9rj04cn6prv6453dgpli2wgkkdzb1r8wa2z13h0lrxfm0pq",
        "type": "tarball",
        "url": "https://github.com/unknownshadow200/classicube/archive/a7647a1ba1a7eaadf53973eddc821bdfab6a1206.tar.gz",
        "url_template": "https://github.com/<owner>/<repo>/archive/<rev>.tar.gz"
    },
    "efm-langserver": {
        "branch": "master",
        "description": "General purpose Language Server",
        "homepage": "",
        "owner": "mattn",
        "repo": "efm-langserver",
        "rev": "cac0b90f5e89667d6202dec21ae20abaa38ac1d5",
        "sha256": "16xsggw0piq2iihlmq339rr1kx5q52ff42yx3msgk65l8za9xsa4",
        "type": "tarball",
        "url": "https://github.com/mattn/efm-langserver/archive/cac0b90f5e89667d6202dec21ae20abaa38ac1d5.tar.gz",
        "url_template": "https://github.com/<owner>/<repo>/archive/<rev>.tar.gz"
    },
    "emacs": {
        "branch": "master",
        "description": null,
        "homepage": null,
        "owner": "crazazy",
        "repo": "emacs",
        "rev": "da3219009af5ff6693d6a586551f108decf6605e",
        "sha256": "1xkjnr1yary814p9ipvr39a4100a0fj0g4san2x3832f1dbdsliw",
        "type": "tarball",
        "url": "https://github.com/crazazy/emacs/archive/da3219009af5ff6693d6a586551f108decf6605e.tar.gz",
        "url_template": "https://github.com/<owner>/<repo>/archive/<rev>.tar.gz"
    },
    "home-manager": {
        "branch": "master",
        "description": "Manage a user environment using Nix",
        "homepage": "https://rycee.gitlab.io/home-manager/",
        "owner": "rycee",
        "repo": "home-manager",
        "rev": "1ee1d01daa19b3a6d16b5fb680c31a2bc110ce24",
        "sha256": "0g45bwiq6dyq74am8kfnzx6ipyjiq967icyy71bcr3c4kfch34pm",
        "type": "tarball",
        "url": "https://github.com/rycee/home-manager/archive/1ee1d01daa19b3a6d16b5fb680c31a2bc110ce24.tar.gz",
        "url_template": "https://github.com/<owner>/<repo>/archive/<rev>.tar.gz"
    },
    "impermanence": {
        "branch": "master",
        "description": "Modules to help you handle persistent state on systems with ephemeral root storage [maintainer=@talyz]",
        "homepage": "",
        "owner": "nix-community",
        "repo": "impermanence",
        "rev": "58558845bc68dcf2bb32caa80564f7fe3f6cbc61",
        "sha256": "10z3g4knkvq838zbfq71pkfyl8cffrpavna448wf5mjscycp0gnv",
        "type": "tarball",
        "url": "https://github.com/nix-community/impermanence/archive/58558845bc68dcf2bb32caa80564f7fe3f6cbc61.tar.gz",
        "url_template": "https://github.com/<owner>/<repo>/archive/<rev>.tar.gz"
    },
    "napalm": {
        "branch": "master",
        "description": "Support for building npm packages in Nix and lightweight npm registry",
        "homepage": "",
        "owner": "nmattia",
        "repo": "napalm",
        "rev": "7c0c62207b6e70168dab91ba85d7d2568c3e0157",
        "sha256": "0f0x5kail7lrv471y9s9yy1mh7zpdma58x4ikya6cvh59yy5052z",
        "type": "tarball",
        "url": "https://github.com/nmattia/napalm/archive/7c0c62207b6e70168dab91ba85d7d2568c3e0157.tar.gz",
        "url_template": "https://github.com/<owner>/<repo>/archive/<rev>.tar.gz"
    },
    "niv": {
        "branch": "master",
        "description": "Easy dependency management for Nix projects",
        "homepage": "https://github.com/nmattia/niv",
        "owner": "nmattia",
        "repo": "niv",
        "rev": "af958e8057f345ee1aca714c1247ef3ba1c15f5e",
        "sha256": "1qjavxabbrsh73yck5dcq8jggvh3r2jkbr6b5nlz5d9yrqm9255n",
        "type": "tarball",
        "url": "https://github.com/nmattia/niv/archive/af958e8057f345ee1aca714c1247ef3ba1c15f5e.tar.gz",
        "url_template": "https://github.com/<owner>/<repo>/archive/<rev>.tar.gz"
    },
    "nix-gen-node-tools": {
        "branch": "master",
        "description": "generate nix expressions for downloading node CLI tools",
        "homepage": null,
        "owner": "crazazy",
        "repo": "nix-gen-node-tools",
        "rev": "f3f61bb103fa11e3d7c9be6b5caa8b6bb96c8b3e",
        "sha256": "1j5qxjgkdw0gw10arcliw8mx07nkxcah9bvnhv7kpcyjzpm6nd9j",
        "type": "tarball",
        "url": "https://github.com/crazazy/nix-gen-node-tools/archive/f3f61bb103fa11e3d7c9be6b5caa8b6bb96c8b3e.tar.gz",
        "url_template": "https://github.com/<owner>/<repo>/archive/<rev>.tar.gz"
    },
    "nixpkgs": {
        "branch": "nixos-unstable",
        "description": "Nix Packages collection",
        "homepage": "",
        "owner": "nixos",
        "repo": "nixpkgs",
        "rev": "758b29b5a28b818e311ad540637a5c1e40867489",
        "sha256": "00nk1a002zzi0ij4xp2hf7955wj49qdwsm2wy7mzbpjbgick6scp",
        "type": "tarball",
        "url": "https://github.com/nixos/nixpkgs/archive/758b29b5a28b818e311ad540637a5c1e40867489.tar.gz",
        "url_template": "https://github.com/<owner>/<repo>/archive/<rev>.tar.gz"
    }
}
