{
    "NUR": {
        "branch": "master",
        "description": "Nix User Repository: User contributed nix packages [maintainer=@Mic92]",
        "homepage": "",
        "owner": "nix-community",
        "repo": "NUR",
        "rev": "0cec1dcf9cc1f2bdeb8972ad6edd9ee20b5fb301",
        "sha256": "05jm8zaw0vd6ggmslv85zy80m9cssy6ad91pj70k69m84l9nfsrq",
        "type": "tarball",
        "url": "https://github.com/nix-community/NUR/archive/0cec1dcf9cc1f2bdeb8972ad6edd9ee20b5fb301.tar.gz",
        "url_template": "https://github.com/<owner>/<repo>/archive/<rev>.tar.gz"
    },
    "classicube": {
        "branch": "master",
        "description": "Custom Minecraft Classic / ClassiCube client written in C (formerly ClassicalSharp in C#) from scratch.",
        "homepage": "",
        "owner": "unknownshadow200",
        "repo": "classicube",
        "rev": "e88a6b59096384a54f9b688ef37a1f8e1a23bb3c",
        "sha256": "1nfl5znkayr41kams16paqlbr7d5jlgrlcbdphvzsv7g996yz88m",
        "type": "tarball",
        "url": "https://github.com/unknownshadow200/classicube/archive/e88a6b59096384a54f9b688ef37a1f8e1a23bb3c.tar.gz",
        "url_template": "https://github.com/<owner>/<repo>/archive/<rev>.tar.gz"
    },
    "efm-langserver": {
        "branch": "master",
        "description": "General purpose Language Server",
        "homepage": "",
        "owner": "mattn",
        "repo": "efm-langserver",
        "rev": "a0e967e16b0715c697e0e4fc91c601f65ff3931c",
        "sha256": "1hbiaj3drhm85gv3jh86gvcvm7wjainjmvqjqhca444sx95i8mvn",
        "type": "tarball",
        "url": "https://github.com/mattn/efm-langserver/archive/a0e967e16b0715c697e0e4fc91c601f65ff3931c.tar.gz",
        "url_template": "https://github.com/<owner>/<repo>/archive/<rev>.tar.gz"
    },
    "emacs": {
        "branch": "master",
        "description": null,
        "homepage": null,
        "owner": "crazazy",
        "repo": "emacs",
        "rev": "c6f542c5de0cac21a6d1e401ea69bba873b95a4d",
        "sha256": "1qj669vasx3gq40r3m6nl3vckx8vadbdqn7cxn5byjg1yk1mw59d",
        "type": "tarball",
        "url": "https://github.com/crazazy/emacs/archive/c6f542c5de0cac21a6d1e401ea69bba873b95a4d.tar.gz",
        "url_template": "https://github.com/<owner>/<repo>/archive/<rev>.tar.gz"
    },
    "flake-utils": {
        "branch": "master",
        "description": "Pure Nix flake utility functions",
        "flake": true,
        "homepage": null,
        "owner": "numtide",
        "repo": "flake-utils",
        "rev": "7e5bf3925f6fbdfaf50a2a7ca0be2879c4261d19",
        "sha256": "1l6xijmnk04rgm98b67l1lpsb5w8yzfar55apr5sbiggkibhqm6x",
        "type": "tarball",
        "url": "https://github.com/numtide/flake-utils/archive/7e5bf3925f6fbdfaf50a2a7ca0be2879c4261d19.tar.gz",
        "url_template": "https://github.com/<owner>/<repo>/archive/<rev>.tar.gz"
    },
    "gitignore": {
        "branch": "master",
        "description": "Nix function for filtering local git sources",
        "homepage": "",
        "owner": "hercules-ci",
        "repo": "gitignore",
        "rev": "80463148cd97eebacf80ba68cf0043598f0d7438",
        "sha256": "1l34rmh4lf4w8a1r8vsvkmg32l1chl0p593fl12r28xx83vn150v",
        "type": "tarball",
        "url": "https://github.com/hercules-ci/gitignore/archive/80463148cd97eebacf80ba68cf0043598f0d7438.tar.gz",
        "url_template": "https://github.com/<owner>/<repo>/archive/<rev>.tar.gz"
    },
    "home-manager": {
        "branch": "master",
        "description": "Manage a user environment using Nix",
        "flake": true,
        "homepage": "https://rycee.gitlab.io/home-manager/",
        "owner": "rycee",
        "repo": "home-manager",
        "rev": "66d9dbfa36f59748e06bb30cd98b3f4ad76cd482",
        "sha256": "1n3rl7jh73vjpbhs0pcxjnkk6fpvqllbinlz5zjx9y1wv2vmfial",
        "type": "tarball",
        "url": "https://github.com/rycee/home-manager/archive/66d9dbfa36f59748e06bb30cd98b3f4ad76cd482.tar.gz",
        "url_template": "https://github.com/<owner>/<repo>/archive/<rev>.tar.gz"
    },
    "impermanence": {
        "branch": "master",
        "description": "Modules to help you handle persistent state on systems with ephemeral root storage [maintainer=@talyz]",
        "flake": true,
        "homepage": "",
        "owner": "nix-community",
        "repo": "impermanence",
        "rev": "58558845bc68dcf2bb32caa80564f7fe3f6cbc61",
        "sha256": "10z3g4knkvq838zbfq71pkfyl8cffrpavna448wf5mjscycp0gnv",
        "type": "tarball",
        "url": "https://github.com/nix-community/impermanence/archive/58558845bc68dcf2bb32caa80564f7fe3f6cbc61.tar.gz",
        "url_template": "https://github.com/<owner>/<repo>/archive/<rev>.tar.gz"
    },
    "napalm": {
        "branch": "master",
        "description": "Support for building npm packages in Nix and lightweight npm registry",
        "flake": true,
        "homepage": "",
        "owner": "nix-community",
        "repo": "napalm",
        "rev": "b60e529d203284a6680c4adec766ad20d885bab2",
        "sha256": "1xaqz0l7hf6wqy4wsv92rvp3mgncxl9qgdc0wrd2y6scgjd01z8s",
        "type": "tarball",
        "url": "https://github.com/nix-community/napalm/archive/b60e529d203284a6680c4adec766ad20d885bab2.tar.gz",
        "url_template": "https://github.com/<owner>/<repo>/archive/<rev>.tar.gz"
    },
    "niv": {
        "branch": "master",
        "description": "Easy dependency management for Nix projects",
        "homepage": "https://github.com/nmattia/niv",
        "owner": "nmattia",
        "repo": "niv",
        "rev": "65a61b147f307d24bfd0a5cd56ce7d7b7cc61d2e",
        "sha256": "17mirpsx5wyw262fpsd6n6m47jcgw8k2bwcp1iwdnrlzy4dhcgqh",
        "type": "tarball",
        "url": "https://github.com/nmattia/niv/archive/65a61b147f307d24bfd0a5cd56ce7d7b7cc61d2e.tar.gz",
        "url_template": "https://github.com/<owner>/<repo>/archive/<rev>.tar.gz"
    },
    "nix-doom-emacs": {
        "branch": "master",
        "description": "doom-emacs packaged for Nix",
        "flake": true,
        "homepage": "",
        "owner": "vlaci",
        "repo": "nix-doom-emacs",
        "rev": "fee14d217b7a911aad507679dafbeaa8c1ebf5ff",
        "sha256": "1g0izscjh5nv4n0n1m58jc6z27i9pkbxs17mnb05a83ffdbmmva6",
        "type": "tarball",
        "url": "https://github.com/vlaci/nix-doom-emacs/archive/fee14d217b7a911aad507679dafbeaa8c1ebf5ff.tar.gz",
        "url_template": "https://github.com/<owner>/<repo>/archive/<rev>.tar.gz"
    },
    "nix-gen-node-tools": {
        "branch": "master",
        "description": "generate nix expressions for downloading node CLI tools",
        "homepage": null,
        "owner": "crazazy",
        "repo": "nix-gen-node-tools",
        "rev": "f3f61bb103fa11e3d7c9be6b5caa8b6bb96c8b3e",
        "sha256": "1j5qxjgkdw0gw10arcliw8mx07nkxcah9bvnhv7kpcyjzpm6nd9j",
        "type": "tarball",
        "url": "https://github.com/crazazy/nix-gen-node-tools/archive/f3f61bb103fa11e3d7c9be6b5caa8b6bb96c8b3e.tar.gz",
        "url_template": "https://github.com/<owner>/<repo>/archive/<rev>.tar.gz"
    },
    "nixpkgs": {
        "branch": "nixos-unstable",
        "description": "Nix Packages collection",
        "flake": true,
        "homepage": "",
        "owner": "nixos",
        "repo": "nixpkgs",
        "rev": "82155ff501c7622cb2336646bb62f7624261f6d7",
        "sha256": "0xv47cpgaxb4j46ggjx9gkg299m9cdfzar27xw5h5k2lg5d3dljg",
        "type": "tarball",
        "url": "https://github.com/nixos/nixpkgs/archive/82155ff501c7622cb2336646bb62f7624261f6d7.tar.gz",
        "url_template": "https://github.com/<owner>/<repo>/archive/<rev>.tar.gz"
    }
}
