{
    "niv": {
        "branch": "master",
        "description": "Easy dependency management for Nix projects",
        "homepage": "https://github.com/nmattia/niv",
        "owner": "nmattia",
        "repo": "niv",
        "rev": "af958e8057f345ee1aca714c1247ef3ba1c15f5e",
        "sha256": "1qjavxabbrsh73yck5dcq8jggvh3r2jkbr6b5nlz5d9yrqm9255n",
        "type": "tarball",
        "url": "https://github.com/nmattia/niv/archive/af958e8057f345ee1aca714c1247ef3ba1c15f5e.tar.gz",
        "url_template": "https://github.com/<owner>/<repo>/archive/<rev>.tar.gz"
    },
    "nixpkgs": {
        "branch": "nixos-unstable",
        "description": "Nix Packages collection",
        "homepage": "https://github.com/NixOS/nixpkgs",
        "owner": "NixOS",
        "repo": "nixpkgs",
        "rev": "29a15e2c1f5ad64c235d78ba5e29a56fe520ad45",
        "sha256": "16i9i090pzxh713acmmhlg4jy06hckwfjsxx1y0pdhihishrk378",
        "type": "tarball",
        "url": "https://github.com/NixOS/nixpkgs/archive/29a15e2c1f5ad64c235d78ba5e29a56fe520ad45.tar.gz",
        "url_template": "https://github.com/<owner>/<repo>/archive/<rev>.tar.gz"
    },
    "nixpkgs-master": {
        "branch": "master",
        "description": "Nix Packages collection",
        "homepage": "",
        "owner": "NixOS",
        "repo": "nixpkgs",
        "rev": "65aeed59c52c572eccdf9237ce45d9fb0fd18b91",
        "sha256": "1aiwagbw2kwn08zrg44v9vf68dysjm1k79vxsrxs1311nf4dvrj4",
        "type": "tarball",
        "url": "https://github.com/NixOS/nixpkgs/archive/65aeed59c52c572eccdf9237ce45d9fb0fd18b91.tar.gz",
        "url_template": "https://github.com/<owner>/<repo>/archive/<rev>.tar.gz"
    },
    "nixpkgs-unstable": {
        "branch": "nixpkgs-unstable",
        "description": "Nix Packages collection",
        "homepage": "https://github.com/NixOS/nixpkgs",
        "owner": "NixOS",
        "repo": "nixpkgs",
        "rev": "f6803b46e8ab57ad737fd82052370a3d847b7fa7",
        "sha256": "06v8hzh0aj4ij96wvf3kk6id9wbqzrr9znfhdvkzmb1yp53mr6d7",
        "type": "tarball",
        "url": "https://github.com/NixOS/nixpkgs/archive/f6803b46e8ab57ad737fd82052370a3d847b7fa7.tar.gz",
        "url_template": "https://github.com/<owner>/<repo>/archive/<rev>.tar.gz"
    }
}
