{
  "satty": {
    "cargoLocks": {
      "Cargo.lock": [
        "./satty-c757d4cd8a2c6eddf5722b8759e0b430a1186f3b/Cargo.lock",
        {}
      ]
    },
    "date": "2023-12-07",
    "extract": null,
    "name": "satty",
    "passthru": null,
    "pinned": false,
    "src": {
      "deepClone": false,
      "fetchSubmodules": false,
      "leaveDotGit": false,
      "name": null,
      "owner": "gabm",
      "repo": "Satty",
      "rev": "c757d4cd8a2c6eddf5722b8759e0b430a1186f3b",
      "sha256": "sha256-cb/Xw+Sr4OFctLEwm/RRFpUmvGExr1OXcZtK/w3nkLA=",
      "type": "github"
    },
    "version": "c757d4cd8a2c6eddf5722b8759e0b430a1186f3b"
  }
}
