{
  "name": "RPCS3",
  "version": "0.0.40-19192",
  "source": {
    "type": "github-release",
    "skip_prerelease": true,
    "name_query": "[0].name"
  },
  "platforms": {
    "aarch64-darwin": {
      "repo": "RPCS3/rpcs3-binaries-mac-arm64",
      "file": "rpcs3-v0.0.40-19192-72fa4098_macos_aarch64.7z",
      "query": "[0].assets[0].name",
      "hash": "sha256-yCWYT3SUR8q6eKZBxJtxseK7Sh2seqMPwNHL1Uu7GN8=",
      "version": "build-72fa4098dcdbaedaca9ba0ae858e9d4e23afd94a"
    },
    "x86_64-darwin": {
      "repo": "RPCS3/rpcs3-binaries-mac",
      "file": "rpcs3-v0.0.40-19192-72fa4098_macos.7z",
      "query": "[0].assets[0].name",
      "hash": "sha256-sRFBpHoQLDPN1h/ZpDLmUILTS5s5ZVuWgmiYkmdy29g=",
      "version": "build-72fa4098dcdbaedaca9ba0ae858e9d4e23afd94a"
    }
  }
}