{
  "name": "Heroic",
  "source": {
    "type": "github-release",
    "repo": "Heroic-Games-Launcher/HeroicGamesLauncher",
    "skipPrerelease": true,
    "tag_prefix": "v"
  },
  "version": "2.19.1",
  "platforms": {
    "aarch64-darwin": {
      "file": "Heroic-{version}-macOS-arm64.zip",
      "hash": "sha256-jQ9bB2oEwMw7QtplVlKAYkuBrE3ah8qwNBURyJgzOz0="
    },
    "x86_64-darwin": {
      "file": "Heroic-{version}-macOS-x64.zip",
      "hash": "sha256-Ig9eiuj6P+F5VzF2pj6xzYuX1bovDfHKGL0w5lxj7ew="
    }
  }
}